mosaic_widget/__init__.py
mosaic_widget/frame_interop.py
mosaic_widget/static/index.css
mosaic_widget/static/index.js
mosaic_widget/tests/__init__.py
mosaic_widget/tests/test_frame_interop.py
mosaic_widget-0.20.1.dist-info/METADATA
mosaic_widget-0.20.1.dist-info/WHEEL
mosaic_widget-0.20.1.dist-info/RECORD
