Metadata-Version: 2.4
Name: mosaic-widget
Version: 0.20.1
Summary: A Jupyter widget for Mosaic
Project-URL: homepage, https://github.com/uwdata/mosaic
Requires-Python: >=3.10
Requires-Dist: anywidget>=0.9.0
Requires-Dist: duckdb>=1.3.1
Requires-Dist: narwhals>=1.46.0
Requires-Dist: pyarrow
